LICENSE.md
MANIFEST.in
setup.py
dashboards_bundlers/__init__.py
dashboards_bundlers/_version.py
dashboards_bundlers/server_download.py
dashboards_bundlers/server_upload.py
jupyter_dashboards_bundlers.egg-info/PKG-INFO
jupyter_dashboards_bundlers.egg-info/SOURCES.txt
jupyter_dashboards_bundlers.egg-info/dependency_links.txt
jupyter_dashboards_bundlers.egg-info/requires.txt
jupyter_dashboards_bundlers.egg-info/top_level.txt
test/test_server_download.py
test/test_server_upload.py